papa_events/__init__.py
papa_events/application.py
papa_events/config.py
papa_events/event.py
papa_events/exceptions.py
papa_events-0.107.0.dist-info/licenses/LICENSE
papa_events-0.107.0.dist-info/METADATA
papa_events-0.107.0.dist-info/WHEEL
papa_events-0.107.0.dist-info/top_level.txt
papa_events-0.107.0.dist-info/RECORD
