Metadata-Version: 2.4
Name: papa-events
Version: 0.107.0
Summary: Libreria para gestion de eventos en python
Requires-Python: <3.15,>=3.13
License-File: LICENSE
Requires-Dist: aio-pika<10.0.0,>=9.5.7
Requires-Dist: asyncpg>=0.30.0
Requires-Dist: pydantic-settings<3.0.0,>=2.11.0
Requires-Dist: pydantic<3.0.0,>=2.12.2
Requires-Dist: opentelemetry-instrumentation-aio-pika<1.0,>=0.58b0
Dynamic: license-file
